LICENSE.txt
README.md
setup.cfg
setup.py
photocrypt/__init__.py
photocrypt/photocrypt.py
photocrypt.egg-info/PKG-INFO
photocrypt.egg-info/SOURCES.txt
photocrypt.egg-info/dependency_links.txt
photocrypt.egg-info/requires.txt
photocrypt.egg-info/top_level.txt
photocrypt/core/__init__.py
photocrypt/core/bdata.py
photocrypt/core/bstream.py
photocrypt/core/cipher.py
photocrypt/core/image.py
photocrypt/core/packer.py
photocrypt/crypto/AES.py
photocrypt/crypto/RSA.py
photocrypt/crypto/__init__.py
photocrypt/image/__init__.py
photocrypt/image/bitmap.py
photocrypt/image/crypto_bitmap.py
photocrypt/utils/__init__.py
photocrypt/utils/keymgr.py