Metadata-Version: 2.1
Name: photocrypt
Version: 0.0.1
Summary: A package that can encrypt and decrypt images
Home-page: https://github.com/Kullmann/RSAPhotoCryptography
Author: Hosung Lee, Sean Kullman
Author-email: runway3237@gmail.com, seankullmann@gmail.com
License: UNKNOWN
Project-URL: Bug Reports, https://github.com/Kullmann/RSAPhotoCryptography/issues
Project-URL: Source, https://github.com/Kullmann/RSAPhotoCryptography
Keywords: cryptology,cryptograpy,image
Platform: UNKNOWN
Classifier: Development Status :: 3 - Alpha
Classifier: Programming Language :: Python :: 3
Classifier: License :: OSI Approved :: MIT License
Classifier: Operating System :: OS Independent
Classifier: Programming Language :: Python :: 3
Classifier: Programming Language :: Python :: 3.5
Classifier: Programming Language :: Python :: 3.6
Classifier: Programming Language :: Python :: 3.7
Classifier: Programming Language :: Python :: 3.8
Classifier: Programming Language :: Python :: 3 :: Only
Requires-Python: >=3.6
Provides-Extra: gui
